pyparsing_ext
